hypso/DataArrayDict.py
hypso/DataArrayValidator.py
hypso/Hypso.py
hypso/HypsoBase.py
hypso/__init__.py
hypso/hypso1.py
hypso/hypso2.py
hypso/atmospheric_correction/__init__.py
hypso/atmospheric_correction/atmospheric_correction.py
hypso/atmospheric_correction/atmospheric_correction_6sv1.py
hypso/atmospheric_correction/atmospheric_correction_acolite.py
hypso/atmospheric_correction/atmospheric_correction_machi.py
hypso/atmospheric_correction/base.py
hypso/calibration/__init__.py
hypso/calibration/calibration_pipeline.py
hypso/calibration/calibration_pipeline_functions.py
hypso/calibration/correction.py
hypso/calibration/destriping.py
hypso/calibration/make_destriping_matrix.py
hypso/calibration/radiometric.py
hypso/calibration/smile.py
hypso/calibration/srf.py
hypso/chlorophyll_estimation/plsr.py
hypso/chlorophyll_estimation/sort/__init__.py
hypso/chlorophyll_estimation/sort/band_ratio_chlorophyll_estimation.py
hypso/chlorophyll_estimation/sort/chl_algorithms.py
hypso/chlorophyll_estimation/sort/chlorophyll_estimation.py
hypso/chlorophyll_estimation/sort/indices.py
hypso/chlorophyll_estimation/sort/tuned_chlorophyll_estimation.py
hypso/chlorophyll_estimation/sort/utils.py
hypso/chlorophyll_estimation/sort/data/hypso_wl_headers.csv
hypso/classification/__init__.py
hypso/classification/jon_cnn_classifier.py
hypso/classification/jonas_svm_classifier.py
hypso/classification/water.py
hypso/classification/WaterDetection/WaterDetect.ini
hypso/classification/WaterDetection/__init__.py
hypso/classification/WaterDetection/runWaterDetect.py
hypso/classification/WaterDetection/auxdata/dogliotti.txt
hypso/classification/WaterDetection/auxdata/nechad_2016_L8.txt
hypso/classification/WaterDetection/auxdata/nechad_2016_S2.txt
hypso/classification/WaterDetection/waterdetect/Common.py
hypso/classification/WaterDetection/waterdetect/External_mask.py
hypso/classification/WaterDetection/waterdetect/Glint.py
hypso/classification/WaterDetection/waterdetect/Image.py
hypso-2.1.2.dist-info/METADATA
hypso-2.1.2.dist-info/WHEEL
hypso-2.1.2.dist-info/top_level.txt
hypso-2.1.2.dist-info/RECORD
